minio_async_client/__init__.py
minio_async_client/api.py
minio_async_client/item/__init__.py
minio_async_client/item/bucket.py
minio_async_client/item/item.py
minio_async_client/item/method_http_request.py
minio_async_client/item/token.py
minio_async_client/session/__init__.py
minio_async_client-0.0.8.dist-info/METADATA
minio_async_client-0.0.8.dist-info/WHEEL
minio_async_client-0.0.8.dist-info/RECORD
