Metadata-Version: 2.1
Name: minio_async_client
Version: 0.0.8
Summary: Library for working with minio (S3 storage)
Author: triks
Author-email: trik0001000@gmail.com
Requires-Python: >=3.12,<4.0
Classifier: Programming Language :: Python :: 3
Classifier: Programming Language :: Python :: 3.12
Requires-Dist: aiohttp[speedups] (>=3.9.3,<4.0.0)
Requires-Dist: boto3 (>=1.34.79,<2.0.0)
Requires-Dist: minio (>=7.2.5,<8.0.0)
Requires-Dist: requests (>=2.31.0,<3.0.0)
Requires-Dist: xmltodict (>=0.13.0,<0.14.0)
